euclidemu2/.DS_Store
euclidemu2/__init__.py
euclidemu2/_euclidemu2.cpython-312-darwin.so
euclidemu2/cosmo.cxx
euclidemu2/cosmo.h
euclidemu2/ee2_bindata.dat
euclidemu2/emulator.cxx
euclidemu2/emulator.h
euclidemu2/euclidemu2.cpp
euclidemu2/euclidemu2.pyx
euclidemu2/units_and_constants.h
euclidemu2-1.4.3.dist-info/licenses/LICENSE
euclidemu2-1.4.3.dist-info/METADATA
euclidemu2-1.4.3.dist-info/WHEEL
euclidemu2-1.4.3.dist-info/top_level.txt
euclidemu2-1.4.3.dist-info/RECORD
