Metadata-Version: 2.4
Name: euclidemu2
Version: 1.4.3
Summary: Python wrapper for EuclidEmulator2
Home-page: https://github.com/PedroCarrilho/EuclidEmulator2/tree/pywrapper
Author: Pedro Carrilho,  Mischa Knabenhans
Author-email: pedromgcarrilho@gmail.com
License-File: LICENSE
Requires-Dist: numpy
Requires-Dist: scipy
Dynamic: author
Dynamic: author-email
Dynamic: description
Dynamic: description-content-type
Dynamic: home-page
Dynamic: license-file
Dynamic: requires-dist
Dynamic: summary
